mds_mdspwrstripbackup-0.1.2.dist-info/METADATA
mds_mdspwrstripbackup-0.1.2.dist-info/RECORD
mds_mdspwrstripbackup-0.1.2.dist-info/WHEEL
mds_mdspwrstripbackup-0.1.2.dist-info/top_level.txt
mdspwrstripbackup/__init__.py
mdspwrstripbackup/backuppwrstrip.py
mdspwrstripbackup/backupserver2exthd.py
mdspwrstripbackup/check_switch_device.py
mdspwrstripbackup/epccontrol2.pl
mdspwrstripbackup/gude.py
mdspwrstripbackup/nonepwr.py
mdspwrstripbackup/example/bk_read_konfig.py
mdspwrstripbackup/example/bk_run_backup.py
mdspwrstripbackup/example/bk_write_konfig.py
